aind_hpc_client/__init__.py
aind_hpc_client/api_client.py
aind_hpc_client/api_response.py
aind_hpc_client/configuration.py
aind_hpc_client/exceptions.py
aind_hpc_client/py.typed
aind_hpc_client/rest.py
aind_hpc_client/api/__init__.py
aind_hpc_client/api/default_api.py
aind_hpc_client/api/slurm_api.py
aind_hpc_client/models/__init__.py
aind_hpc_client/models/dbv0036_account.py
aind_hpc_client/models/dbv0036_account_info.py
aind_hpc_client/models/dbv0036_account_response.py
aind_hpc_client/models/dbv0036_association.py
aind_hpc_client/models/dbv0036_association_max.py
aind_hpc_client/models/dbv0036_association_max_jobs.py
aind_hpc_client/models/dbv0036_association_max_tres.py
aind_hpc_client/models/dbv0036_association_max_tres_minutes.py
aind_hpc_client/models/dbv0036_association_max_tres_minutes_per.py
aind_hpc_client/models/dbv0036_association_max_tres_per.py
aind_hpc_client/models/dbv0036_association_short_info.py
aind_hpc_client/models/dbv0036_associations_info.py
aind_hpc_client/models/dbv0036_cluster_info.py
aind_hpc_client/models/dbv0036_cluster_info_associations.py
aind_hpc_client/models/dbv0036_config_info.py
aind_hpc_client/models/dbv0036_config_response.py
aind_hpc_client/models/dbv0036_coordinator_info.py
aind_hpc_client/models/dbv0036_diag.py
aind_hpc_client/models/dbv0036_error.py
aind_hpc_client/models/dbv0036_job.py
aind_hpc_client/models/dbv0036_job_exit_code.py
aind_hpc_client/models/dbv0036_job_info.py
aind_hpc_client/models/dbv0036_job_state.py
aind_hpc_client/models/dbv0036_job_step.py
aind_hpc_client/models/dbv0036_job_step_tres.py
aind_hpc_client/models/dbv0036_job_step_tres_requested.py
aind_hpc_client/models/dbv0036_job_tres.py
aind_hpc_client/models/dbv0036_qos.py
aind_hpc_client/models/dbv0036_qos_info.py
aind_hpc_client/models/dbv0036_qos_limits.py
aind_hpc_client/models/dbv0036_qos_limits_max.py
aind_hpc_client/models/dbv0036_qos_limits_max_jobs.py
aind_hpc_client/models/dbv0036_qos_limits_max_jobs_per.py
aind_hpc_client-0.0.5.dist-info/LICENSE
aind_hpc_client-0.0.5.dist-info/METADATA
aind_hpc_client-0.0.5.dist-info/WHEEL
aind_hpc_client-0.0.5.dist-info/top_level.txt
aind_hpc_client-0.0.5.dist-info/RECORD
