Metadata-Version: 2.1
Name: aind-hpc-client
Version: 0.0.5
Summary: Slurm Rest API
Home-page: 
Author: SchedMD LLC
Author-email: sales@schedmd.com
License: Apache 2.0
Keywords: OpenAPI,OpenAPI-Generator,Slurm Rest API
License-File: LICENSE
Requires-Dist: urllib3 <2.1.0,>=1.25.3
Requires-Dist: python-dateutil
Requires-Dist: pydantic >=2
Requires-Dist: typing-extensions >=4.7.1
